core/__init__.py
core/utils.py
xdist-0.0.0.dist-info/LICENSE
xdist-0.0.0.dist-info/METADATA
xdist-0.0.0.dist-info/WHEEL
xdist-0.0.0.dist-info/top_level.txt
xdist-0.0.0.dist-info/RECORD
