Metadata-Version: 2.1
Name: xdist
Version: 0.0.0
Summary: Python library of word2vec-based similiarity embeddings
Home-page: https://github.com/doerlbh/xdist
Author: Baihan Lin
Author-email: doerlbh@gmail.com
License: MIT
Project-URL: Bug Tracker, https://github.com/doerlbh/xdist/issues
Platform: UNKNOWN
Classifier: Programming Language :: Python :: 3
Classifier: License :: OSI Approved :: MIT License
Classifier: Operating System :: OS Independent
Requires-Python: >=3.6
License-File: LICENSE
Requires-Dist: numpy (>=1.16.5)
Requires-Dist: pandas
